{
  "total": 251087400,
  "groupedByArea": [
    {
      "area": "ด้านการดำเนินงานอื่น ๆ ",
      "total": 17452380,
      "plans": [
        {
          "plan": "งบกลาง",
          "total": 17452380
        }
      ]
    },
    {
      "area": "ด้านบริหารทั่วไป",
      "total": 71564320,
      "plans": [
        {
          "plan": "บริหารงานทั่วไป",
          "total": 70071120
        },
        {
          "plan": "การรักษาความสงบภายใน",
          "total": 1493200
        }
      ]
    },
    {
      "area": "ด้านบริการชุมชนและสังคม",
      "total": 75455900,
      "plans": [
        {
          "plan": "การศึกษา",
          "total": 21637800
        },
        {
          "plan": "สาธารณสุข",
          "total": 20595500
        },
        {
          "plan": "สังคมสงเคราะห์",
          "total": 952300
        },
        {
          "plan": "เคหะและชุมชน",
          "total": 560000
        },
        {
          "plan": "สร้างความเข้มแข็งของชุมชน",
          "total": 3497400
        },
        {
          "plan": "การศาสนา วัฒนธรรม และนันทนาการ",
          "total": 28212900
        }
      ]
    },
    {
      "area": "ด้านการเศรษฐกิจ",
      "total": 86614800,
      "plans": [
        {
          "plan": "อุตสาหกรรมและการโยธา",
          "total": 84272800
        },
        {
          "plan": "การเกษตร",
          "total": 2300000
        },
        {
          "plan": "การพาณิชย์",
          "total": 42000
        }
      ]
    }
  ],
  "groupedByType": [
    {
      "type": "งบกลาง",
      "total": 17452380
    },
    {
      "type": "งบบุคลากร",
      "total": 87871020
    },
    {
      "type": "งบดำเนินงาน",
      "total": 88508900
    },
    {
      "type": "งบลงทุน",
      "total": 54955100
    },
    {
      "type": "งบเงินอุดหนุน",
      "total": 2300000
    }
  ],
  "tasks": [
    {
      "task": "งบกลาง",
      "area": "ด้านการดำเนินงานอื่น ๆ ",
      "plan": "งบกลาง",
      "type": "งบกลาง",
      "total": 17452380
    },
    {
      "task": "บริหารทั่วไป",
      "area": "ด้านบริหารทั่วไป",
      "plan": "บริหารงานทั่วไป",
      "type": "งบบุคลากร",
      "total": 30498920
    },
    {
      "task": "บริหารทั่วไป",
      "area": "ด้านบริหารทั่วไป",
      "plan": "บริหารงานทั่วไป",
      "type": "งบดำเนินงาน",
      "total": 17210000
    },
    {
      "task": "บริหารทั่วไป",
      "area": "ด้านบริหารทั่วไป",
      "plan": "บริหารงานทั่วไป",
      "type": "งบลงทุน",
      "total": 239300
    },
    {
      "task": "วางแผนสถิติและวิชาการ",
      "area": "ด้านบริหารทั่วไป",
      "plan": "บริหารงานทั่วไป",
      "type": "งบบุคลากร",
      "total": 3902300
    },
    {
      "task": "วางแผนสถิติและวิชาการ",
      "area": "ด้านบริหารทั่วไป",
      "plan": "บริหารงานทั่วไป",
      "type": "งบดำเนินงาน",
      "total": 810000
    },
    {
      "task": "วางแผนสถิติและวิชาการ",
      "area": "ด้านบริหารทั่วไป",
      "plan": "บริหารงานทั่วไป",
      "type": "งบลงทุน",
      "total": 38700
    },
    {
      "task": "บริหารงานคลัง",
      "area": "ด้านบริหารทั่วไป",
      "plan": "บริหารงานทั่วไป",
      "type": "งบบุคลากร",
      "total": 9051900
    },
    {
      "task": "บริหารงานคลัง",
      "area": "ด้านบริหารทั่วไป",
      "plan": "บริหารงานทั่วไป",
      "type": "งบดำเนินงาน",
      "total": 7536500
    },
    {
      "task": "บริหารงานคลัง",
      "area": "ด้านบริหารทั่วไป",
      "plan": "บริหารงานทั่วไป",
      "type": "งบลงทุน",
      "total": 90700
    },
    {
      "task": "ควบคุมภายในและการตรวจสอบภายใน",
      "area": "ด้านบริหารทั่วไป",
      "plan": "บริหารงานทั่วไป",
      "type": "งบบุคลากร",
      "total": 639800
    },
    {
      "task": "ควบคุมภายในและการตรวจสอบภายใน",
      "area": "ด้านบริหารทั่วไป",
      "plan": "บริหารงานทั่วไป",
      "type": "งบดำเนินงาน",
      "total": 53000
    },
    {
      "task": "ป้องกันและบรรเทาสาธารณภัย",
      "area": "ด้านบริหารทั่วไป",
      "plan": "การรักษาความสงบภายใน",
      "type": "งบบุคลากร",
      "total": 1493200
    },
    {
      "task": "บริหารทั่วไปเกี่ยวกับการศึกษา",
      "area": "ด้านบริการชุมชนและสังคม",
      "plan": "การศึกษา",
      "type": "งบบุคลากร",
      "total": 11709800
    },
    {
      "task": "บริหารทั่วไปเกี่ยวกับการศึกษา",
      "area": "ด้านบริการชุมชนและสังคม",
      "plan": "การศึกษา",
      "type": "งบดำเนินงาน",
      "total": 5886600
    },
    {
      "task": "บริหารทั่วไปเกี่ยวกับการศึกษา",
      "area": "ด้านบริการชุมชนและสังคม",
      "plan": "การศึกษา",
      "type": "งบลงทุน",
      "total": 212500
    },
    {
      "task": "ระดับก่อนวัยเรียนและประถมศึกษา",
      "area": "ด้านบริการชุมชนและสังคม",
      "plan": "การศึกษา",
      "type": "งบดำเนินงาน",
      "total": 628900
    },
    {
      "task": "ศึกษาไม่กำหนดระดับ",
      "area": "ด้านบริการชุมชนและสังคม",
      "plan": "การศึกษา",
      "type": "งบดำเนินงาน",
      "total": 3200000
    },
    {
      "task": "บริหารทั่วไปเกี่ยวกับสาธารณสุข",
      "area": "ด้านบริการชุมชนและสังคม",
      "plan": "สาธารณสุข",
      "type": "งบบุคลากร",
      "total": 1710400
    },
    {
      "task": "บริหารทั่วไปเกี่ยวกับสาธารณสุข",
      "area": "ด้านบริการชุมชนและสังคม",
      "plan": "สาธารณสุข",
      "type": "งบดำเนินงาน",
      "total": 665400
    },
    {
      "task": "งานโรงพยาบาล",
      "area": "ด้านบริการชุมชนและสังคม",
      "plan": "สาธารณสุข",
      "type": "งบบุคลากร",
      "total": 5660800
    },
    {
      "task": "งานโรงพยาบาล",
      "area": "ด้านบริการชุมชนและสังคม",
      "plan": "สาธารณสุข",
      "type": "งบดำเนินงาน",
      "total": 11288000
    },
    {
      "task": "งานโรงพยาบาล",
      "area": "ด้านบริการชุมชนและสังคม",
      "plan": "สาธารณสุข",
      "type": "งบลงทุน",
      "total": 546400
    },
    {
      "task": "บริการสาธารณสุขและงานสาธารณสุขอื่น",
      "area": "ด้านบริการชุมชนและสังคม",
      "plan": "สาธารณสุข",
      "type": "งบบุคลากร",
      "total": 724500
    },
    {
      "task": "สวัสดิการสังคมและสังคมสงเคราะห์",
      "area": "ด้านบริการชุมชนและสังคม",
      "plan": "สังคมสงเคราะห์",
      "type": "งบบุคลากร",
      "total": 902300
    },
    {
      "task": "สวัสดิการสังคมและสังคมสงเคราะห์",
      "area": "ด้านบริการชุมชนและสังคม",
      "plan": "สังคมสงเคราะห์",
      "type": "งบดำเนินงาน",
      "total": 50000
    },
    {
      "task": "สวนสาธารณะ",
      "area": "ด้านบริการชุมชนและสังคม",
      "plan": "เคหะและชุมชน",
      "type": "งบดำเนินงาน",
      "total": 500000
    },
    {
      "task": "กำจัดขยะมูลฝอยและสิ่งปฏิกูล",
      "area": "ด้านบริการชุมชนและสังคม",
      "plan": "เคหะและชุมชน",
      "type": "งบดำเนินงาน",
      "total": 60000
    },
    {
      "task": "ส่งเสริมและสนับสนุนความเข้มแข็งชุมชน",
      "area": "ด้านบริการชุมชนและสังคม",
      "plan": "สร้างความเข้มแข็งของชุมชน",
      "type": "งบบุคลากร",
      "total": 247400
    },
    {
      "task": "ส่งเสริมและสนับสนุนความเข้มแข็งชุมชน",
      "area": "ด้านบริการชุมชนและสังคม",
      "plan": "สร้างความเข้มแข็งของชุมชน",
      "type": "งบดำเนินงาน",
      "total": 3250000
    },
    {
      "task": "บริหารทั่วไปเกี่ยวกับศาสนา วัฒนธรม และนันทนาการ",
      "area": "ด้านบริการชุมชนและสังคม",
      "plan": "การศาสนา วัฒนธรรม และนันทนาการ",
      "type": "งบบุคลากร",
      "total": 545300
    },
    {
      "task": "บริหารทั่วไปเกี่ยวกับศาสนา วัฒนธรม และนันทนาการ",
      "area": "ด้านบริการชุมชนและสังคม",
      "plan": "การศาสนา วัฒนธรรม และนันทนาการ",
      "type": "งบดำเนินงาน",
      "total": 114000
    },
    {
      "task": "บริหารทั่วไปเกี่ยวกับศาสนา วัฒนธรม และนันทนาการ",
      "area": "ด้านบริการชุมชนและสังคม",
      "plan": "การศาสนา วัฒนธรรม และนันทนาการ",
      "type": "งบลงทุน",
      "total": 25000
    },
    {
      "task": "กีฬาและนันทนาการ",
      "area": "ด้านบริการชุมชนและสังคม",
      "plan": "การศาสนา วัฒนธรรม และนันทนาการ",
      "type": "งบบุคลากร",
      "total": 2234200
    },
    {
      "task": "กีฬาและนันทนาการ",
      "area": "ด้านบริการชุมชนและสังคม",
      "plan": "การศาสนา วัฒนธรรม และนันทนาการ",
      "type": "งบดำเนินงาน",
      "total": 8880500
    },
    {
      "task": "กีฬาและนันทนาการ",
      "area": "ด้านบริการชุมชนและสังคม",
      "plan": "การศาสนา วัฒนธรรม และนันทนาการ",
      "type": "งบลงทุน",
      "total": 2750200
    },
    {
      "task": "กีฬาและนันทนาการ",
      "area": "ด้านบริการชุมชนและสังคม",
      "plan": "การศาสนา วัฒนธรรม และนันทนาการ",
      "type": "งบเงินอุดหนุน",
      "total": 2000000
    },
    {
      "task": "ศาสนาวัฒนธรรมท้องถิ่น",
      "area": "ด้านบริการชุมชนและสังคม",
      "plan": "การศาสนา วัฒนธรรม และนันทนาการ",
      "type": "งบดำเนินงาน",
      "total": 6100000
    },
    {
      "task": "วิชาการวางแผนและส่งเสริมการท่องเที่ยว",
      "area": "ด้านบริการชุมชนและสังคม",
      "plan": "การศาสนา วัฒนธรรม และนันทนาการ",
      "type": "งบบุคลากร",
      "total": 840700
    },
    {
      "task": "วิชาการวางแผนและส่งเสริมการท่องเที่ยว",
      "area": "ด้านบริการชุมชนและสังคม",
      "plan": "การศาสนา วัฒนธรรม และนันทนาการ",
      "type": "งบดำเนินงาน",
      "total": 3100000
    },
    {
      "task": "วิชาการวางแผนและส่งเสริมการท่องเที่ยว",
      "area": "ด้านบริการชุมชนและสังคม",
      "plan": "การศาสนา วัฒนธรรม และนันทนาการ",
      "type": "งบลงทุน",
      "total": 1623000
    },
    {
      "task": "บริหารทั่วไปเกี่ยวกับอุตสาหกรรมและการโยธา",
      "area": "ด้านการเศรษฐกิจ",
      "plan": "อุตสาหกรรมและการโยธา",
      "type": "งบบุคลากร",
      "total": 2500200
    },
    {
      "task": "บริหารทั่วไปเกี่ยวกับอุตสาหกรรมและการโยธา",
      "area": "ด้านการเศรษฐกิจ",
      "plan": "อุตสาหกรรมและการโยธา",
      "type": "งบดำเนินงาน",
      "total": 17176000
    },
    {
      "task": "บริหารทั่วไปเกี่ยวกับอุตสาหกรรมและการโยธา",
      "area": "ด้านการเศรษฐกิจ",
      "plan": "อุตสาหกรรมและการโยธา",
      "type": "งบลงทุน",
      "total": 50300
    },
    {
      "task": "ก่อสร้าง",
      "area": "ด้านการเศรษฐกิจ",
      "plan": "อุตสาหกรรมและการโยธา",
      "type": "งบบุคลากร",
      "total": 15209300
    },
    {
      "task": "ก่อสร้าง",
      "area": "ด้านการเศรษฐกิจ",
      "plan": "อุตสาหกรรมและการโยธา",
      "type": "งบลงทุน",
      "total": 49337000
    },
    {
      "task": "ส่งเสริมการเกษตร",
      "area": "ด้านการเศรษฐกิจ",
      "plan": "การเกษตร",
      "type": "งบดำเนินงาน",
      "total": 1850000
    },
    {
      "task": "ส่งเสริมการเกษตร",
      "area": "ด้านการเศรษฐกิจ",
      "plan": "การเกษตร",
      "type": "งบเงินอุดหนุน",
      "total": 300000
    },
    {
      "task": "สิ่งแวดล้อมและทรัพยากรธรรมชาติ",
      "area": "ด้านการเศรษฐกิจ",
      "plan": "การเกษตร",
      "type": "งบดำเนินงาน",
      "total": 150000
    },
    {
      "task": "กิจการสถานีขนส่ง/กิจการท่าเรือ",
      "area": "ด้านการเศรษฐกิจ",
      "plan": "การพาณิชย์",
      "type": "งบลงทุน",
      "total": 42000
    }
  ],
  "pao": {
    "name": "ระนอง",
    "incomes": [
      {
        "type": "รายได้จัดเก็บเอง",
        "total": 15538700,
        "categories": [
          {
            "category": "หมวดภาษีอากร",
            "total": 9000000
          },
          {
            "category": "หมวดค่าธรรมเนียม \nค่าปรับและใบอนุญาต",
            "total": 656700
          },
          {
            "category": "หมวดรายได้จากทรัพย์สิน",
            "total": 5770000
          },
          {
            "category": "หมวดรายได้เบ็ดเตล็ด",
            "total": 62000
          },
          {
            "category": "หมวดรายได้จากทุน",
            "total": 50000
          }
        ]
      },
      {
        "type": "รายได้จากภาษีที่รัฐบาลจัดเก็บแล้วจัดสรรให้",
        "total": 160890000,
        "categories": [
          {
            "category": "หมวดภาษีจัดสรร",
            "total": 160890000
          }
        ]
      },
      {
        "type": "รายได้ที่รัฐบาลอุดหนุนให้",
        "total": 74658700,
        "categories": [
          {
            "category": "หมวดเงินอุดหนุนทั่วไป",
            "total": 74658700
          }
        ]
      }
    ],
    "population": 179694,
    "chiefExecutives": [
      {
        "name": "นาย ธนกร บริสุทธิญาณี",
        "inOffice": "20/12/2563 - 19/12/2567",
        "photoUrl": "https://ele.dla.go.th/download/ELE/Candidate/20210316/3EE24F23-5167-20F2-9083-8E0DC1A3A1F5_UPLOADFILE_DlaELE63.jpg",
        "ownAccount": {
          "asset": 34315108,
          "debt": 6509479.81,
          "income": 2699880,
          "expense": 2304767.8,
          "taxed": 113422.63
        },
        "spouseAccount": {
          "asset": 5536099.55,
          "debt": 2650817.31,
          "income": 600000,
          "expense": 519600,
          "taxed": 0
        },
        "childrenAccount": {
          "asset": 0,
          "debt": 0,
          "income": 0,
          "expense": 0
        },
        "fillingUrl": "https://drive.google.com/drive/folders/1O5NLxus4y_hT0aawJngL7o1bqsfUdPqZ?usp=sharing"
      }
    ],
    "budgetingDocUrl": "https://drive.google.com/file/d/128o_eD1QppFt0Ew04CKgfuvahT99C8Yq/view?usp=drive_link",
    "actAiUrl": "https://tinyurl.com/yb8p54x9"
  }
}